{
  "meta": {
    "class": 8,
    "chapter": 6,
    "title": "Squares and Square Roots",
    "subject": "Mathematics",
    "board": "CBSE",
    "totalMarks": 40,
    "duration": 45
  },
  "sections": {
    "A": {
      "type": "mcq",
      "title": "Section A — Multiple Choice Questions",
      "marks": 1,
      "questions": [
        {
          "id": "A1",
          "q": "Which of the following is NOT a perfect square?",
          "opts": ["121", "169", "250", "196"],
          "ans": "250",
          "hint": "Check last digit and prime factorization"
        },
        {
          "id": "A2",
          "q": "The square root of 2.25 is:",
          "opts": ["0.15", "1.5", "15", "0.5"],
          "ans": "1.5",
          "hint": "2.25 = 225/100"
        },
        {
          "id": "A3",
          "q": "How many non-perfect-square numbers lie between 5² and 6²?",
          "opts": ["8", "10", "11", "5"],
          "ans": "10",
          "hint": "Between n² and (n+1)² there are 2n numbers"
        },
        {
          "id": "A4",
          "q": "The sum of first 9 odd numbers is:",
          "opts": ["81", "72", "64", "100"],
          "ans": "81",
          "hint": "Sum of first n odd numbers = n²"
        },
        {
          "id": "A5",
          "q": "Which number must be multiplied by 50 to make it a perfect square?",
          "opts": ["2", "5", "8", "10"],
          "ans": "2",
          "hint": "50 = 2×5². Which prime is unpaired?"
        },
        {
          "id": "A6",
          "q": "√(49/81) equals:",
          "opts": ["7/81", "49/9", "7/9", "9/7"],
          "ans": "7/9",
          "hint": "√(p/q) = √p/√q"
        },
        {
          "id": "A7",
          "q": "The least number to subtract from 190 to make it a perfect square is:",
          "opts": ["1", "2", "3", "4"],
          "ans": "1",
          "hint": "13² = 169, 14² = 196. Find the nearest perfect square below 190"
        },
        {
          "id": "A8",
          "q": "A number ending in which digit cannot be a perfect square?",
          "opts": ["1", "5", "8", "9"],
          "ans": "8",
          "hint": "Perfect squares only end in 0,1,4,5,6,9"
        },
        {
          "id": "A9",
          "q": "√7056 equals:",
          "opts": ["82", "84", "86", "88"],
          "ans": "84",
          "hint": "7056 = 2⁴×3²×7²"
        },
        {
          "id": "A10",
          "q": "If the area of a square is 1764 cm², its perimeter is:",
          "opts": ["168 cm", "168 cm", "168 cm", "168 cm"],
          "ans": "168 cm",
          "hint": "√1764 = 42, perimeter = 4×42"
        }
      ]
    },
    "B": {
      "type": "short1",
      "title": "Section B — Short Answer I (2 marks each)",
      "marks": 2,
      "questions": [
        {
          "id": "B1",
          "q": "Find √1225 using prime factorisation.",
          "ans": "1225 = 5² × 7². √1225 = 5 × 7 = 35",
          "hint": "Group prime factors in pairs"
        },
        {
          "id": "B2",
          "q": "Find the smallest number by which 180 must be multiplied to make it a perfect square.",
          "ans": "180 = 2²×3²×5. Factor 5 is unpaired. Multiply by 5. Answer: 5",
          "hint": "Find the unpaired prime factor"
        },
        {
          "id": "B3",
          "q": "Is 1000 a perfect square? Give reason.",
          "ans": "No. 1000 = 2³×5³. Factor 2 appears 3 times (odd power), so it cannot be paired completely. Not a perfect square.",
          "hint": "Check if all prime factors appear in pairs"
        },
        {
          "id": "B4",
          "q": "Find √0.0064.",
          "ans": "0.0064 = 64/10000. √64=8, √10000=100. √0.0064 = 8/100 = 0.08",
          "hint": "Convert to fraction first"
        },
        {
          "id": "B5",
          "q": "Write 81 as the sum of consecutive odd numbers.",
          "ans": "81 = 9². Sum of first 9 odd numbers: 1+3+5+7+9+11+13+15+17 = 81",
          "hint": "n² = sum of first n odd numbers"
        }
      ]
    },
    "C": {
      "type": "short2",
      "title": "Section C — Short Answer II (3 marks each)",
      "marks": 3,
      "questions": [
        {
          "id": "C1",
          "q": "Find √1764 using the long division method.",
          "ans": "Pair digits: 17|64. Largest square ≤17 is 16=4². Remainder=1, bring down 64→164. Double quotient: 8. Find d: 82×2=164. √1764 = 42.",
          "hint": "Group digits in pairs from right"
        },
        {
          "id": "C2",
          "q": "Find the smallest number to be subtracted from 500 to make it a perfect square. Also find the square root of the resulting number.",
          "ans": "22²=484, 23²=529. 529>500, so nearest below is 484. Subtract 500−484=16. √484=22.",
          "hint": "Find the perfect square just below 500"
        },
        {
          "id": "C3",
          "q": "A school arranges 2025 students in a square array. Find the number of rows.",
          "ans": "n² = 2025. √2025: 2025=3⁴×5²=(3²×5)²=45². √2025=45. So 45 rows with 45 students each.",
          "hint": "Find √2025"
        }
      ]
    },
    "D": {
      "type": "long",
      "title": "Section D — Long Answer (5 marks each)",
      "marks": 5,
      "questions": [
        {
          "id": "D1",
          "q": "Using the long division method, find √7056. Also verify your answer.",
          "ans": "Group: 70|56. Largest square ≤70 is 64=8². Remainder=6, bring down 56→656. Double quotient: 16. Try d=4: 164×4=656 ✓. √7056=84. Verify: 84²=84×84=7056 ✓.",
          "hint": "Long division method for square root"
        },
        {
          "id": "D2",
          "q": "Prove that the product of two perfect squares is always a perfect square. Give two examples to verify.",
          "ans": "Let m=a² and n=b². Then m×n=a²×b²=(ab)², which is a perfect square (square of ab). Example 1: 4×9=36=6² ✓. Example 2: 25×16=400=20² ✓. Hence proved.",
          "hint": "Use algebraic proof with variables"
        }
      ]
    }
  }
}
