{
  "chapter_slug": "a-peek-beyond-the-point",
  "chapter_name": "A Peek Beyond the Point",
  "chapter_emoji": "🔍",
  "class_num": 7,
  "board": "cbse",
  "topic": "arithmetic",
  "chap_id": 3,
  "exam_key": "c7-03",
  "intro_text": "Hi <span class=\"hl\" id=\"sName\">there</span>! Get ready to explore the fascinating world of decimal numbers! We&#39;ll uncover how they work and make calculations super easy. ✨🔢",
  "complete_message": "Fantastic job! You&#39;ve mastered decimals! Keep up the great work! 🎉",
  "explain_questions": [
    {
      "id": "q1",
      "question": "What is the place value of the digit 7 in the number 12.375?",
      "question_spoken": "What is the place value of the digit seven in the number twelve point three seven five?",
      "steps": [
        {
          "t": "Identify the decimal point.",
          "s": "First, locate the decimal point in the number. It separates the whole number part from the fractional part."
        },
        {
          "t": "Count places to the right of the decimal.",
          "s": "Now, count the positions of the digits to the right of the decimal point. The first place is tenths, the second is hundredths, and so on."
        },
        {
          "t": "Name the place value of 7.",
          "s": "Since 7 is in the second position after the decimal point, its place value is hundredths."
        }
      ],
      "confirm_question": "What is the place value of 4 in 0.49?",
      "confirm_question_spoken": "What is the place value of four in zero point four nine?",
      "answers": [
        "Hundredths",
        "0.07",
        "7/100"
      ],
      "nudges": [
        "Remember, digits to the right of the decimal point represent parts of a whole.",
        "The first digit after the decimal is in the 'tenths' place. What about the second?",
        "The digit 7 is in the hundredths place."
      ],
      "anim_svg": "<g id=\"q1s0\" opacity=\"0\"><text x=\"22\" y=\"28\" font-size=\"11\" font-weight=\"800\" fill=\"#5a4a30\">Identify the decimal point.</text></g><g id=\"q1s1\" opacity=\"0\"><text x=\"22\" y=\"68\" font-size=\"11\" font-weight=\"800\" fill=\"#5a4a30\">Count places to the right of the decimal.</text></g><g id=\"q1s2\" opacity=\"0\"><text x=\"22\" y=\"108\" font-size=\"11\" font-weight=\"800\" fill=\"#5a4a30\">Name the place value of 7.</text></g><g id=\"q1ans\" opacity=\"0\"><rect x=\"40\" y=\"148\" width=\"320\" height=\"24\" rx=\"7\" fill=\"#eef2eb\" stroke=\"#6b4c2a\" stroke-width=\"1.5\"/><text x=\"210\" y=\"163\" text-anchor=\"middle\" font-family=\"Share Tech Mono\" font-size=\"12\" font-weight=\"bold\" fill=\"#7a8c6e\">Hundredths</text></g>"
    },
    {
      "id": "q2",
      "question": "How do you read the decimal number 5.23?",
      "question_spoken": "How do you read the decimal number five point two three?",
      "steps": [
        {
          "t": "Read the whole number part.",
          "s": "Start by reading the digits before the decimal point as a whole number."
        },
        {
          "t": "Say 'point' for the decimal.",
          "s": "Next, say the word 'point' to indicate the decimal separator."
        },
        {
          "t": "Read digits after the decimal individually.",
          "s": "Finally, read each digit after the decimal point separately, not as a whole number."
        }
      ],
      "confirm_question": "How do you read 10.05?",
      "confirm_question_spoken": "How do you read ten point zero five?",
      "answers": [
        "Five point two three"
      ],
      "nudges": [
        "Think about how you'd tell someone this number over the phone.",
        "Do you read the digits after the decimal as a single number or individually?",
        "You read it as 'Five point two three'."
      ],
      "anim_svg": "<g id=\"q2s0\" opacity=\"0\"><text x=\"22\" y=\"28\" font-size=\"11\" font-weight=\"800\" fill=\"#5a4a30\">Read the whole number part.</text></g><g id=\"q2s1\" opacity=\"0\"><text x=\"22\" y=\"68\" font-size=\"11\" font-weight=\"800\" fill=\"#5a4a30\">Say 'point' for the decimal.</text></g><g id=\"q2s2\" opacity=\"0\"><text x=\"22\" y=\"108\" font-size=\"11\" font-weight=\"800\" fill=\"#5a4a30\">Read digits after the decimal individually.</text></g><g id=\"q2ans\" opacity=\"0\"><rect x=\"40\" y=\"148\" width=\"320\" height=\"24\" rx=\"7\" fill=\"#eef2eb\" stroke=\"#6b4c2a\" stroke-width=\"1.5\"/><text x=\"210\" y=\"163\" text-anchor=\"middle\" font-family=\"Share Tech Mono\" font-size=\"12\" font-weight=\"bold\" fill=\"#7a8c6e\">Five point two three</text></g>"
    },
    {
      "id": "q3",
      "question": "Convert the fraction 3/10 to a decimal.",
      "question_spoken": "Convert the fraction three tenths to a decimal.",
      "steps": [
        {
          "t": "Understand the denominator.",
          "s": "The denominator, 10, tells us that the number has one decimal place, representing tenths."
        },
        {
          "t": "Place the numerator after the decimal.",
          "s": "Since it's 3 tenths, the digit 3 will be in the tenths place, which is the first digit after the decimal point."
        },
        {
          "t": "Write the decimal.",
          "s": "So, with a zero in the ones place, the decimal form is 0.3."
        }
      ],
      "confirm_question": "Convert 7/100 to a decimal.",
      "confirm_question_spoken": "Convert seven hundredths to a decimal.",
      "answers": [
        "0.3"
      ],
      "nudges": [
        "Remember, the number of zeros in the denominator (10, 100, 1000) tells you how many decimal places there will be.",
        "Since the denominator is 10, there will be one digit after the decimal point.",
        "The decimal form is 0.3."
      ],
      "anim_svg": "<g id=\"q3s0\" opacity=\"0\"><text x=\"22\" y=\"28\" font-size=\"11\" font-weight=\"800\" fill=\"#5a4a30\">Understand the denominator.</text></g><g id=\"q3s1\" opacity=\"0\"><text x=\"22\" y=\"68\" font-size=\"11\" font-weight=\"800\" fill=\"#5a4a30\">Place the numerator after the decimal.</text></g><g id=\"q3s2\" opacity=\"0\"><text x=\"22\" y=\"108\" font-size=\"11\" font-weight=\"800\" fill=\"#5a4a30\">Write the decimal.</text></g><g id=\"q3ans\" opacity=\"0\"><rect x=\"40\" y=\"148\" width=\"320\" height=\"24\" rx=\"7\" fill=\"#eef2eb\" stroke=\"#6b4c2a\" stroke-width=\"1.5\"/><text x=\"210\" y=\"163\" text-anchor=\"middle\" font-family=\"Share Tech Mono\" font-size=\"12\" font-weight=\"bold\" fill=\"#7a8c6e\">0.3</text></g>"
    },
    {
      "id": "q4",
      "question": "Which is greater: 0.5 or 0.45?",
      "question_spoken": "Which is greater: zero point five or zero point four five?",
      "steps": [
        {
          "t": "Make the number of decimal places equal.",
          "s": "To compare easily, add a zero to 0.5 to make it 0.50. Now both numbers have two decimal places."
        },
        {
          "t": "Compare the whole number parts.",
          "s": "Both numbers have 0 as their whole number part, so we move to the decimal part."
        },
        {
          "t": "Compare digits from left to right.",
          "s": "Now compare 0.50 and 0.45. The tenths digit in 0.50 is 5, and in 0.45 it is 4. Since 5 is greater than 4, 0.50 is greater."
        }
      ],
      "confirm_question": "Which is smaller: 1.2 or 1.25?",
      "confirm_question_spoken": "Which is smaller: one point two or one point two five?",
      "answers": [
        "0.5"
      ],
      "nudges": [
        "It helps to make the number of decimal places the same for both numbers.",
        "Think of 0.5 as 50 paise and 0.45 as 45 paise.",
        "0.5 is greater than 0.45."
      ],
      "anim_svg": "<g id=\"q4s0\" opacity=\"0\"><text x=\"22\" y=\"28\" font-size=\"11\" font-weight=\"800\" fill=\"#5a4a30\">Make the number of decimal places equal.</text></g><g id=\"q4s1\" opacity=\"0\"><text x=\"22\" y=\"68\" font-size=\"11\" font-weight=\"800\" fill=\"#5a4a30\">Compare the whole number parts.</text></g><g id=\"q4s2\" opacity=\"0\"><text x=\"22\" y=\"108\" font-size=\"11\" font-weight=\"800\" fill=\"#5a4a30\">Compare digits from left to right.</text></g><g id=\"q4ans\" opacity=\"0\"><rect x=\"40\" y=\"148\" width=\"320\" height=\"24\" rx=\"7\" fill=\"#eef2eb\" stroke=\"#6b4c2a\" stroke-width=\"1.5\"/><text x=\"210\" y=\"163\" text-anchor=\"middle\" font-family=\"Share Tech Mono\" font-size=\"12\" font-weight=\"bold\" fill=\"#7a8c6e\">0.5</text></g>"
    },
    {
      "id": "q5",
      "question": "Add 3.25 and 1.7.",
      "question_spoken": "Add three point two five and one point seven.",
      "steps": [
        {
          "t": "Line up the decimal points.",
          "s": "Write the numbers one below the other, making sure their decimal points are perfectly aligned."
        },
        {
          "t": "Add zeros to equalize decimal places.",
          "s": "To make addition easier, add a zero to 1.7 so it becomes 1.70. Now both numbers have two decimal places."
        },
        {
          "t": "Add column by column.",
          "s": "Start adding from the rightmost column, just like with whole numbers. Carry over if needed, and place the decimal point in the sum directly below the others."
        }
      ],
      "confirm_question": "What is 2.1 + 0.55?",
      "confirm_question_spoken": "What is two point one plus zero point five five?",
      "answers": [
        "4.95"
      ],
      "nudges": [
        "Remember to align the decimal points before you start adding.",
        "You can add a zero to 1.7 to make it 1.70.",
        "The sum is 4.95."
      ],
      "anim_svg": "<g id=\"q5s0\" opacity=\"0\"><text x=\"22\" y=\"28\" font-size=\"11\" font-weight=\"800\" fill=\"#5a4a30\">Line up the decimal points.</text></g><g id=\"q5s1\" opacity=\"0\"><text x=\"22\" y=\"68\" font-size=\"11\" font-weight=\"800\" fill=\"#5a4a30\">Add zeros to equalize decimal places.</text></g><g id=\"q5s2\" opacity=\"0\"><text x=\"22\" y=\"108\" font-size=\"11\" font-weight=\"800\" fill=\"#5a4a30\">Add column by column.</text></g><g id=\"q5ans\" opacity=\"0\"><rect x=\"40\" y=\"148\" width=\"320\" height=\"24\" rx=\"7\" fill=\"#eef2eb\" stroke=\"#6b4c2a\" stroke-width=\"1.5\"/><text x=\"210\" y=\"163\" text-anchor=\"middle\" font-family=\"Share Tech Mono\" font-size=\"12\" font-weight=\"bold\" fill=\"#7a8c6e\">4.95</text></g>"
    },
    {
      "id": "q6",
      "question": "Subtract 2.4 from 5.85.",
      "question_spoken": "Subtract two point four from five point eight five.",
      "steps": [
        {
          "t": "Line up the decimal points.",
          "s": "Write 5.85 and 2.4 one below the other, ensuring their decimal points are aligned."
        },
        {
          "t": "Add zeros to equalize decimal places.",
          "s": "Add a zero to 2.4 to make it 2.40. This helps in subtracting digits in each place value."
        },
        {
          "t": "Subtract column by column.",
          "s": "Start subtracting from the rightmost column. If you need to borrow, do so from the digit to the left. Place the decimal point in the difference directly below the others."
        }
      ],
      "confirm_question": "What is 7.3 - 1.25?",
      "confirm_question_spoken": "What is seven point three minus one point two five?",
      "answers": [
        "3.45"
      ],
      "nudges": [
        "Always align the decimal points first. Think of 2.4 as 2.40.",
        "Subtract the hundredths, then the tenths, then the ones.",
        "The difference is 3.45."
      ],
      "anim_svg": "<g id=\"q6s0\" opacity=\"0\"><text x=\"22\" y=\"28\" font-size=\"11\" font-weight=\"800\" fill=\"#5a4a30\">Line up the decimal points.</text></g><g id=\"q6s1\" opacity=\"0\"><text x=\"22\" y=\"68\" font-size=\"11\" font-weight=\"800\" fill=\"#5a4a30\">Add zeros to equalize decimal places.</text></g><g id=\"q6s2\" opacity=\"0\"><text x=\"22\" y=\"108\" font-size=\"11\" font-weight=\"800\" fill=\"#5a4a30\">Subtract column by column.</text></g><g id=\"q6ans\" opacity=\"0\"><rect x=\"40\" y=\"148\" width=\"320\" height=\"24\" rx=\"7\" fill=\"#eef2eb\" stroke=\"#6b4c2a\" stroke-width=\"1.5\"/><text x=\"210\" y=\"163\" text-anchor=\"middle\" font-family=\"Share Tech Mono\" font-size=\"12\" font-weight=\"bold\" fill=\"#7a8c6e\">3.45</text></g>"
    },
    {
      "id": "q7",
      "question": "Multiply 2.5 by 3.",
      "question_spoken": "Multiply two point five by three.",
      "steps": [
        {
          "t": "Multiply ignoring the decimal point.",
          "s": "First, multiply 25 by 3 as if they were whole numbers. What do you get?"
        },
        {
          "t": "Count decimal places in the original decimal.",
          "s": "Now, look at the original decimal number, 2.5. How many digits are there after the decimal point?"
        },
        {
          "t": "Place the decimal point in the product.",
          "s": "In your product from step 1, count that many places from the right and place the decimal point. So, if 2.5 has one decimal place, your answer will also have one decimal place."
        }
      ],
      "confirm_question": "What is 1.2 x 4?",
      "confirm_question_spoken": "What is one point two multiplied by four?",
      "answers": [
        "7.5"
      ],
      "nudges": [
        "First, multiply 25 by 3.",
        "How many digits are after the decimal in 2.5?",
        "The product is 7.5."
      ],
      "anim_svg": "<g id=\"q7s0\" opacity=\"0\"><text x=\"22\" y=\"28\" font-size=\"11\" font-weight=\"800\" fill=\"#5a4a30\">Multiply ignoring the decimal point.</text></g><g id=\"q7s1\" opacity=\"0\"><text x=\"22\" y=\"68\" font-size=\"11\" font-weight=\"800\" fill=\"#5a4a30\">Count decimal places in the original decimal.</text></g><g id=\"q7s2\" opacity=\"0\"><text x=\"22\" y=\"108\" font-size=\"11\" font-weight=\"800\" fill=\"#5a4a30\">Place the decimal point in the product.</text></g><g id=\"q7ans\" opacity=\"0\"><rect x=\"40\" y=\"148\" width=\"320\" height=\"24\" rx=\"7\" fill=\"#eef2eb\" stroke=\"#6b4c2a\" stroke-width=\"1.5\"/><text x=\"210\" y=\"163\" text-anchor=\"middle\" font-family=\"Share Tech Mono\" font-size=\"12\" font-weight=\"bold\" fill=\"#7a8c6e\">7.5</text></g>"
    },
    {
      "id": "q8",
      "question": "Divide 45.6 by 100.",
      "question_spoken": "Divide forty five point six by one hundred.",
      "steps": [
        {
          "t": "Identify the divisor and its zeros.",
          "s": "The divisor is 100. Count how many zeros are in 100."
        },
        {
          "t": "Move the decimal point to the left.",
          "s": "When dividing by 10, 100, 1000, etc., you move the decimal point to the left. The number of places you move it is equal to the number of zeros in the divisor."
        },
        {
          "t": "Write the final answer.",
          "s": "Since 100 has two zeros, move the decimal point in 45.6 two places to the left. You might need to add a zero in front if there isn't a digit."
        }
      ],
      "confirm_question": "What is 3.7 divided by 10?",
      "confirm_question_spoken": "What is three point seven divided by ten?",
      "answers": [
        "0.456"
      ],
      "nudges": [
        "Dividing by 100 makes the number smaller.",
        "How many places do you need to shift the decimal point to the left?",
        "The result is 0.456."
      ],
      "anim_svg": "<g id=\"q8s0\" opacity=\"0\"><text x=\"22\" y=\"28\" font-size=\"11\" font-weight=\"800\" fill=\"#5a4a30\">Identify the divisor and its zeros.</text></g><g id=\"q8s1\" opacity=\"0\"><text x=\"22\" y=\"68\" font-size=\"11\" font-weight=\"800\" fill=\"#5a4a30\">Move the decimal point to the left.</text></g><g id=\"q8s2\" opacity=\"0\"><text x=\"22\" y=\"108\" font-size=\"11\" font-weight=\"800\" fill=\"#5a4a30\">Write the final answer.</text></g><g id=\"q8ans\" opacity=\"0\"><rect x=\"40\" y=\"148\" width=\"320\" height=\"24\" rx=\"7\" fill=\"#eef2eb\" stroke=\"#6b4c2a\" stroke-width=\"1.5\"/><text x=\"210\" y=\"163\" text-anchor=\"middle\" font-family=\"Share Tech Mono\" font-size=\"12\" font-weight=\"bold\" fill=\"#7a8c6e\">0.456</text></g>"
    },
    {
      "id": "q9",
      "question": "Multiply 0.3 by 0.4.",
      "question_spoken": "Multiply zero point three by zero point four.",
      "steps": [
        {
          "t": "Multiply ignoring decimal points.",
          "s": "First, multiply 3 by 4 as if they were whole numbers. What is that product?"
        },
        {
          "t": "Count total decimal places.",
          "s": "Count the total number of digits after the decimal point in both 0.3 (one place) and 0.4 (one place). Add them up."
        },
        {
          "t": "Place the decimal point in the product.",
          "s": "In the product from step 1, count from the right and place the decimal point according to the total number of decimal places you counted. You might need to add leading zeros."
        }
      ],
      "confirm_question": "What is 0.2 x 0.5?",
      "confirm_question_spoken": "What is zero point two multiplied by zero point five?",
      "answers": [
        "0.12"
      ],
      "nudges": [
        "Multiply 3 by 4 first.",
        "How many decimal places are there in total in 0.3 and 0.4?",
        "The product is 0.12."
      ],
      "anim_svg": "<g id=\"q9s0\" opacity=\"0\"><text x=\"22\" y=\"28\" font-size=\"11\" font-weight=\"800\" fill=\"#5a4a30\">Multiply ignoring decimal points.</text></g><g id=\"q9s1\" opacity=\"0\"><text x=\"22\" y=\"68\" font-size=\"11\" font-weight=\"800\" fill=\"#5a4a30\">Count total decimal places.</text></g><g id=\"q9s2\" opacity=\"0\"><text x=\"22\" y=\"108\" font-size=\"11\" font-weight=\"800\" fill=\"#5a4a30\">Place the decimal point in the product.</text></g><g id=\"q9ans\" opacity=\"0\"><rect x=\"40\" y=\"148\" width=\"320\" height=\"24\" rx=\"7\" fill=\"#eef2eb\" stroke=\"#6b4c2a\" stroke-width=\"1.5\"/><text x=\"210\" y=\"163\" text-anchor=\"middle\" font-family=\"Share Tech Mono\" font-size=\"12\" font-weight=\"bold\" fill=\"#7a8c6e\">0.12</text></g>"
    },
    {
      "id": "q10",
      "question": "Divide 1.2 by 0.3.",
      "question_spoken": "Divide one point two by zero point three.",
      "steps": [
        {
          "t": "Convert divisor to a whole number.",
          "s": "To make division easier, we want the divisor (0.3) to be a whole number. Multiply both the divisor and the dividend (1.2) by the same power of 10 to achieve this."
        },
        {
          "t": "Perform the division.",
          "s": "Now that you have a whole number divisor, perform the division as you would with whole numbers or a decimal by a whole number."
        },
        {
          "t": "Write the final answer.",
          "s": "The result of the division is your final answer."
        }
      ],
      "confirm_question": "What is 2.4 divided by 0.6?",
      "confirm_question_spoken": "What is two point four divided by zero point six?",
      "answers": [
        "4"
      ],
      "nudges": [
        "Try to get rid of the decimal in the divisor (0.3). What do you multiply it by?",
        "If you multiply 0.3 by 10, you must also multiply 1.2 by 10.",
        "The answer is 4."
      ],
      "anim_svg": "<g id=\"q10s0\" opacity=\"0\"><text x=\"22\" y=\"28\" font-size=\"11\" font-weight=\"800\" fill=\"#5a4a30\">Convert divisor to a whole number.</text></g><g id=\"q10s1\" opacity=\"0\"><text x=\"22\" y=\"68\" font-size=\"11\" font-weight=\"800\" fill=\"#5a4a30\">Perform the division.</text></g><g id=\"q10s2\" opacity=\"0\"><text x=\"22\" y=\"108\" font-size=\"11\" font-weight=\"800\" fill=\"#5a4a30\">Write the final answer.</text></g><g id=\"q10ans\" opacity=\"0\"><rect x=\"40\" y=\"148\" width=\"320\" height=\"24\" rx=\"7\" fill=\"#eef2eb\" stroke=\"#6b4c2a\" stroke-width=\"1.5\"/><text x=\"210\" y=\"163\" text-anchor=\"middle\" font-family=\"Share Tech Mono\" font-size=\"12\" font-weight=\"bold\" fill=\"#7a8c6e\">4</text></g>"
    }
  ],
  "practice_questions": [
    {
      "question": "Write the place value of the underlined digit in 15.3**8**2.",
      "question_spoken": "Write the place value of the underlined digit in fifteen point three eight two.",
      "answers": [
        "Hundredths",
        "0.08",
        "8/100"
      ],
      "steps": [
        "Identify the decimal point.",
        "Count the positions to the right of the decimal point.",
        "The second position is the hundredths place."
      ],
      "trick": "The first digit after the decimal is tenths, the second is hundredths, and so on. Just count the spots!",
      "alt": "You can also write its value as 8/100 or 0.08, which clearly shows it's in the hundredths place."
    },
    {
      "question": "Write 'Thirteen point zero five' as a decimal number.",
      "question_spoken": "Write 'Thirteen point zero five' as a decimal number.",
      "answers": [
        "13.05"
      ],
      "steps": [
        "Write the whole number part.",
        "Place the decimal point.",
        "Write the digits after the decimal, ensuring correct place value."
      ],
      "trick": "'Point' tells you where the decimal goes. 'Zero five' means 05 after the decimal, so you need a zero in the tenths place.",
      "alt": "Think of it as 13 + 5/100. Since 5/100 is 0.05, adding them gives 13 + 0.05 = 13.05."
    },
    {
      "question": "Arrange the following decimals in ascending order: 2.3, 2.03, 2.33.",
      "question_spoken": "Arrange the following decimals in ascending order: two point three, two point zero three, two point three three.",
      "answers": [
        "2.03, 2.3, 2.33"
      ],
      "steps": [
        "Equalize the number of decimal places by adding zeros.",
        "Compare the whole number parts.",
        "Compare digits from left to right, starting with the tenths place."
      ],
      "trick": "Add trailing zeros to make all numbers have the same number of decimal places (e.g., 2.30, 2.03, 2.33) then compare them like whole numbers.",
      "alt": "Compare digit by digit from left to right. All have 2 as the whole number. Then compare tenths: 0 in 2.03, 3 in 2.3, 3 in 2.33. So 2.03 is smallest. Then compare hundredths for 2.30 and 2.33: 0 is smaller than 3."
    },
    {
      "question": "Convert 17/1000 to a decimal.",
      "question_spoken": "Convert seventeen thousandths to a decimal.",
      "answers": [
        "0.017"
      ],
      "steps": [
        "Identify the denominator.",
        "Determine the number of decimal places needed.",
        "Place the numerator digits after the decimal, adding leading zeros if necessary."
      ],
      "trick": "The number of zeros in the denominator (1000 has 3 zeros) tells you how many decimal places there will be. So, 17 needs to occupy the last two of the three places.",
      "alt": "Divide 17 by 1000. You can think of it as moving the decimal point in 17 (which is 17.0) three places to the left, resulting in 0.017."
    },
    {
      "question": "Add 4.5 + 2.3.",
      "question_spoken": "Add four point five plus two point three.",
      "answers": [
        "6.8"
      ],
      "steps": [
        "Line up the decimal points vertically.",
        "Add the digits in the tenths column.",
        "Add the digits in the ones column and place the decimal point."
      ],
      "trick": "Line up the decimal points vertically, then add as usual. The decimal point in the answer will be in the same column.",
      "alt": "You can think of it as adding the whole parts (4+2=6) and the decimal parts (0.5+0.3=0.8) separately, then combining them: 6 + 0.8 = 6.8."
    },
    {
      "question": "Subtract 8.7 - 3.2.",
      "question_spoken": "Subtract eight point seven minus three point two.",
      "answers": [
        "5.5"
      ],
      "steps": [
        "Line up the decimal points vertically.",
        "Subtract the digits in the tenths column.",
        "Subtract the digits in the ones column and place the decimal point."
      ],
      "trick": "Just like addition, line up the decimal points vertically and subtract. It's like subtracting whole numbers, but with a decimal point.",
      "alt": "Think of it as 87 tenths minus 32 tenths. 87 - 32 = 55. So, the answer is 55 tenths, which is 5.5."
    },
    {
      "question": "Find the sum of 12.34, 5.6, and 0.789.",
      "question_spoken": "Find the sum of twelve point three four, five point six, and zero point seven eight nine.",
      "answers": [
        "18.729"
      ],
      "steps": [
        "Align all numbers by their decimal points.",
        "Add trailing zeros to make all numbers have the same number of decimal places.",
        "Add column by column from right to left, carrying over as needed."
      ],
      "trick": "Always align the decimal points first. Add zeros to the end of numbers to make them all have the same number of decimal places before adding. This prevents errors!",
      "alt": "Add two numbers first, then add the third. For example, (12.34 + 5.60) = 17.94. Then, 17.94 + 0.789 = 18.729."
    },
    {
      "question": "Subtract 15.75 from 20.",
      "question_spoken": "Subtract fifteen point seven five from twenty.",
      "answers": [
        "4.25"
      ],
      "steps": [
        "Rewrite 20 as a decimal with two places (20.00).",
        "Align the decimal points of 20.00 and 15.75.",
        "Subtract column by column, borrowing when necessary."
      ],
      "trick": "Remember that 20 can be written as 20.00. Align the decimal points and then subtract, just like with whole numbers.",
      "alt": "You can think of it as 2000 hundredths minus 1575 hundredths. 2000 - 1575 = 425. So, the answer is 425 hundredths, or 4.25."
    },
    {
      "question": "Multiply 3.125 by 8.",
      "question_spoken": "Multiply three point one two five by eight.",
      "answers": [
        "25.0",
        "25"
      ],
      "steps": [
        "Multiply 3125 by 8, ignoring the decimal point.",
        "Count the number of decimal places in 3.125.",
        "Place the decimal point in the product by counting from the right."
      ],
      "trick": "Multiply 3125 by 8 first (which is 25000). Then count 3 decimal places in 3.125 and place the decimal point in 25000 to get 25.000 or 25.",
      "alt": "Break it down: (3 x 8) + (0.125 x 8). We know 3 x 8 = 24. And 0.125 is 1/8, so 0.125 x 8 = 1. Therefore, 24 + 1 = 25."
    },
    {
      "question": "Divide 789.2 by 100.",
      "question_spoken": "Divide seven hundred eighty nine point two by one hundred.",
      "answers": [
        "7.892"
      ],
      "steps": [
        "Identify the number of zeros in the divisor (100).",
        "Move the decimal point in the dividend (789.2) to the left.",
        "Move it by the same number of places as there are zeros in the divisor."
      ],
      "trick": "Dividing by 10, 100, 1000 means moving the decimal point to the LEFT by the number of zeros in the divisor. For 100, move it 2 places left.",
      "alt": "Think of it as making the number 100 times smaller. Each digit moves two places to the right in terms of place value. So, 7 hundreds becomes 7 ones, 8 tens becomes 8 tenths, etc."
    },
    {
      "question": "Convert 3.25 to a mixed fraction in simplest form.",
      "question_spoken": "Convert three point two five to a mixed fraction in simplest form.",
      "answers": [
        "3 and 1/4",
        "3 1/4"
      ],
      "steps": [
        "Separate the whole number part from the decimal part.",
        "Convert the decimal part to a fraction (e.g., 0.25 = 25/100).",
        "Simplify the fractional part to its lowest terms."
      ],
      "trick": "The digits after the decimal become the numerator, and the denominator is 1 followed by as many zeros as there are decimal places. Then simplify the fraction.",
      "alt": "3.25 means 3 whole units and 25 hundredths. So, it's 3 + 25/100. Now, simplify 25/100 by dividing both numerator and denominator by their greatest common factor, 25. This gives 1/4. So, the mixed fraction is 3 and 1/4."
    },
    {
      "question": "Rahul bought a book for Rs 125.50 and a pen for Rs 18.75. How much did he spend in total?",
      "question_spoken": "Rahul bought a book for Rupees one hundred twenty five point five zero and a pen for Rupees eighteen point seven five. How much did he spend in total?",
      "answers": [
        "144.25"
      ],
      "steps": [
        "Identify the amounts spent.",
        "Align the decimal points of the amounts.",
        "Add the amounts to find the total expenditure."
      ],
      "trick": "'In total' usually means addition. Make sure to align the decimal points when adding money, just like you would with whole numbers.",
      "alt": "Add the rupee parts first: 125 + 18 = 143. Then add the paise parts: 0.50 + 0.75 = 1.25. Finally, add them together: 143 + 1.25 = 144.25."
    },
    {
      "question": "Calculate 1.5 x 2.4.",
      "question_spoken": "Calculate one point five multiplied by two point four.",
      "answers": [
        "3.6"
      ],
      "steps": [
        "Multiply 15 by 24, ignoring the decimal points.",
        "Count the total number of decimal places in both 1.5 and 2.4.",
        "Place the decimal point in the product by counting from the right."
      ],
      "trick": "Multiply 15 by 24 (which is 360). Then count the total number of decimal places in 1.5 (1 place) and 2.4 (1 place), so 1+1=2 places. Place the decimal in 360 to get 3.60 or 3.6.",
      "alt": "Convert to fractions: 1.5 = 15/10 = 3/2 and 2.4 = 24/10 = 12/5. Then multiply the fractions: (3/2) * (12/5) = 36/10 = 3.6."
    },
    {
      "question": "Divide 4.8 by 0.06.",
      "question_spoken": "Divide four point eight by zero point zero six.",
      "answers": [
        "80"
      ],
      "steps": [
        "Convert the divisor (0.06) to a whole number by multiplying by a power of 10.",
        "Multiply the dividend (4.8) by the same power of 10.",
        "Perform the division with the new whole number divisor."
      ],
      "trick": "To divide by a decimal, first make the divisor a whole number by multiplying both the divisor and the dividend by the same power of 10. Here, multiply both by 100 to get 480 divided by 6.",
      "alt": "Convert to fractions: 4.8 = 48/10 and 0.06 = 6/100. Then, (48/10) / (6/100) = (48/10) * (100/6). Simplify: (48 * 10) / 6 = 8 * 10 = 80."
    },
    {
      "question": "A car covers 18.5 km in 1 liter of petrol. How much distance will it cover in 3.5 liters of petrol?",
      "question_spoken": "A car covers eighteen point five kilometers in one liter of petrol. How much distance will it cover in three point five liters of petrol?",
      "answers": [
        "64.75"
      ],
      "steps": [
        "Identify the distance covered per liter and the total liters.",
        "Multiply the distance per liter by the total liters.",
        "Perform the decimal multiplication and place the decimal point correctly."
      ],
      "trick": "This is a multiplication problem. Multiply the distance covered in 1 liter by the total number of liters. Remember to count decimal places carefully for the final answer.",
      "alt": "Estimate first: 18.5 is close to 20, and 3.5 is close to 3 or 4. So, 20 x 3 = 60 or 20 x 4 = 80. The answer should be in this range. Then do the exact calculation: 18.5 x 3.5 = 64.75."
    }
  ]
}